lazr/__init__.py
lazr/misc.py
lazr/path.py
lazr/config/__init__.py
lazr/config/config.py
lazr-0.0.1.dist-info/METADATA
lazr-0.0.1.dist-info/WHEEL
lazr-0.0.1.dist-info/top_level.txt
lazr-0.0.1.dist-info/RECORD
